matcalc/__init__.py
matcalc/_base.py
matcalc/_cli.py
matcalc/_elasticity.py
matcalc/_eos.py
matcalc/_neb.py
matcalc/_phonon.py
matcalc/_phonon3.py
matcalc/_qha.py
matcalc/_relaxation.py
matcalc/_stability.py
matcalc/_surface.py
matcalc/benchmark.py
matcalc/config.py
matcalc/py.typed
matcalc/units.py
matcalc/utils.py
matcalc/elemental_refs/MatPES-PBE-Element-Refs.json.gz
matcalc/elemental_refs/MatPES-r2SCAN-Element-Refs.json.gz
matcalc-0.3.3.dist-info/licenses/LICENSE
matcalc-0.3.3.dist-info/METADATA
matcalc-0.3.3.dist-info/WHEEL
matcalc-0.3.3.dist-info/entry_points.txt
matcalc-0.3.3.dist-info/top_level.txt
matcalc-0.3.3.dist-info/RECORD
