Metadata-Version: 2.4
Name: matcalc
Version: 0.3.3
Summary: Calculators for materials properties from the potential energy surface.
Author-email: Runze Liu <rul048@ucsd.edu>, Eliott Liu <elliottliu17@gmail.com>, Janosh Riebesell <janosh@lbl.gov>, Ji Qi <j1qi@ucsd.edu>, Shyue Ping Ong <ongsp@ucsd.edu>, Tsz Wai Ko <t1ko@ucsd.edu>
Keywords: AI,deep learning,force field,graph,interatomic potential,machine learning,materials,property prediction,science
Classifier: Development Status :: 4 - Beta
Classifier: Intended Audience :: Science/Research
Classifier: License :: OSI Approved :: BSD License
Classifier: Operating System :: OS Independent
Classifier: Programming Language :: Python :: 3
Classifier: Programming Language :: Python :: 3.10
Classifier: Programming Language :: Python :: 3.11
Classifier: Topic :: Scientific/Engineering :: Chemistry
Classifier: Topic :: Scientific/Engineering :: Information Analysis
Classifier: Topic :: Scientific/Engineering :: Physics
Classifier: Topic :: Software Development :: Libraries :: Python Modules
Requires-Python: >=3.10
License-File: LICENSE
Requires-Dist: ase>=3.23.0
Requires-Dist: numpy<2.0.0
Requires-Dist: scikit-learn>=1.6.1
Requires-Dist: pymatgen>=2025.3.10
Requires-Dist: fsspec>=2025.3.0
Requires-Dist: joblib>=1.4.2
Requires-Dist: phonopy>=2.38.0
Requires-Dist: phono3py>=3.15.0
Provides-Extra: phonon
Requires-Dist: seekpath; extra == "phonon"
Provides-Extra: benchmark
Requires-Dist: matminer>=0.9.3; extra == "benchmark"
Provides-Extra: ace
Requires-Dist: pyace>=0.1.1; extra == "ace"
Provides-Extra: mace
Requires-Dist: mace-torch>=0.3.12; extra == "mace"
Provides-Extra: deepmd
Requires-Dist: deepmd-kit>=3.0.2; extra == "deepmd"
Provides-Extra: grace
Requires-Dist: tensorpotential>=0.5.1; extra == "grace"
Provides-Extra: maml
Requires-Dist: maml>=2025.4.3; extra == "maml"
Provides-Extra: orb
Requires-Dist: orb-models>=0.4.2; extra == "orb"
Requires-Dist: pynanoflann>=0.10.0; extra == "orb"
Provides-Extra: sevennet
Requires-Dist: sevenn>=0.10.4; extra == "sevennet"
Dynamic: license-file
